data_providers/__init__.py
data_providers/aggregator.py
data_providers/data_structures.py
data_providers/delegate.py
data_providers/exceptions.py
data_providers/testing.py
phx_data_providers-3.0.0.dist-info/LICENCE.txt
phx_data_providers-3.0.0.dist-info/METADATA
phx_data_providers-3.0.0.dist-info/WHEEL
phx_data_providers-3.0.0.dist-info/top_level.txt
phx_data_providers-3.0.0.dist-info/RECORD
