Metadata-Version: 2.1
Name: phx-data-providers
Version: 3.0.0
Summary: Generic implementation of the flywheel design pattern.
Author-email: Phoenix Zerin <phx@phx.nz>
License: MIT License
Project-URL: Documentation, https://data-providers.readthedocs.io/en/latest/extension_filters.html#django-filters
Project-URL: Changelog, https://github.com/todofixthis/data-providers/releases
Project-URL: Issues, https://github.com/todofixthis/data-providers/issues
Project-URL: Repository, https://github.com/todofixthis/data-providers
Keywords: aggregator,design patterns,flywheel pattern
Classifier: Development Status :: 5 - Production/Stable
Classifier: Intended Audience :: Developers
Classifier: License :: OSI Approved :: MIT License
Classifier: Programming Language :: Python :: 3
Classifier: Programming Language :: Python :: 3.11
Classifier: Programming Language :: Python :: 3.10
Classifier: Programming Language :: Python :: 3.9
Classifier: Topic :: Software Development :: Libraries :: Python Modules
Classifier: Topic :: Text Processing :: Filters
Requires-Python: >=3.9
License-File: LICENCE.txt
Provides-Extra: build-system
Requires-Dist: build ; extra == 'build-system'
Requires-Dist: twine ; extra == 'build-system'
Provides-Extra: docs-builder
Requires-Dist: sphinx ; extra == 'docs-builder'
Requires-Dist: sphinx-rtd-theme ; extra == 'docs-builder'
Provides-Extra: test-runner
Requires-Dist: tox ; extra == 'test-runner'
